{
  "payload_invalido": {
    "status": 400,
    "code": "PUE-001",
    "title": "Payload invalido",
    "summary": "El body no cumple con el esquema requerido.",
    "source": "body",
    "reason": "Faltan campos obligatorios o el tipo/longitud es incorrecto.",
    "solution": "Envia los campos obligatorios con los tipos correctos.",
    "requiredFields": ["nombre", "areaId"],
    "optionalFields": [],
    "constraints": {
      "nombre": "string 2-150",
      "areaId": "number int > 0"
    },
    "example": {
      "nombre": "Soporte",
      "areaId": 1
    }
  },
  "id_invalido": {
    "status": 400,
    "code": "PUE-002",
    "title": "ID invalido",
    "summary": "El parametro de ruta no es valido.",
    "source": "path",
    "param": "id",
    "reason": "El id no es numerico.",
    "solution": "Envia un id numerico en la ruta.",
    "expected": "number"
  },
  "puesto_no_encontrado": {
    "status": 404,
    "code": "PUE-003",
    "title": "Puesto no encontrado",
    "summary": "No existe un puesto con ese id.",
    "source": "path",
    "param": "id",
    "reason": "El id no existe en base de datos.",
    "solution": "Verifica el id antes de consultar."
  },
  "duplicado": {
    "status": 409,
    "code": "PUE-004",
    "title": "Registro duplicado",
    "summary": "Ya existe un puesto con el mismo nombre en el area.",
    "source": "body",
    "reason": "Violacion de indice unico.",
    "solution": "Usa un nombre diferente dentro del area.",
    "uniqueFields": ["areaId", "nombre"]
  },
  "sin_cambios": {
    "status": 400,
    "code": "PUE-005",
    "title": "Sin cambios",
    "summary": "No se enviaron campos para actualizar.",
    "source": "body",
    "reason": "El body esta vacio o solo contiene campos invalidos.",
    "solution": "Envia al menos un campo valido.",
    "updatableFields": ["nombre", "areaId"]
  },
  "relacion_invalida": {
    "status": 409,
    "code": "PUE-006",
    "title": "Relacion invalida",
    "summary": "El area indicada no existe o hay referencias que impiden la accion.",
    "source": "server",
    "reason": "Restriccion de llave foranea.",
    "solution": "Verifica los ids relacionados antes de guardar o borrar."
  },
  "error_interno": {
    "status": 500,
    "code": "PUE-500",
    "title": "Error interno",
    "summary": "Ocurrio un error inesperado en el servidor.",
    "source": "server",
    "reason": "Excepcion no controlada.",
    "solution": "Intenta mas tarde o revisa los logs del servidor."
  }
}
